tests/__init__.py
tests/test_console_output.py
tests/test_function_decorator.py
tests/test_log_entries.py
tests/test_log_file_creation.py
tests/test_logging_setup.py
tests/test_ui_logger.py
tracemate/__init__.py
tracemate/function_decorator.py
tracemate/init_lib.py
tracemate/logging_setup.py
tracemate-0.1.1.dist-info/METADATA
tracemate-0.1.1.dist-info/WHEEL
tracemate-0.1.1.dist-info/top_level.txt
tracemate-0.1.1.dist-info/RECORD
