Metadata-Version: 2.1
Name: tracemate
Version: 0.1.1
Summary: 🔍 Tracemate: A comprehensive tracing and logging toolkit for Python CLI applications.
Home-page: https://github.com/alexfigueroa-solutions/tracemate
Author: Alex Figueroa
Author-email: alexfigueroa.solutions@gmail.com
License: MIT
Classifier: Development Status :: 3 - Alpha
Classifier: Intended Audience :: Developers
Classifier: License :: OSI Approved :: MIT License
Classifier: Programming Language :: Python :: 3.6
Classifier: Programming Language :: Python :: 3.7
Classifier: Programming Language :: Python :: 3.8
Classifier: Programming Language :: Python :: 3.9
Requires-Dist: iniconfig ==2.0.0
Requires-Dist: markdown-it-py
Requires-Dist: mdurl ==0.1.2
Requires-Dist: packaging ==23.2
Requires-Dist: pluggy ==1.3.0
Requires-Dist: Pygments ==2.16.1
Requires-Dist: pytest ==7.4.3
Requires-Dist: rich ==13.6.0
